movers/__init__.py
movers/ansi.py
movers/ansitowin32.py
movers/initialise.py
movers/win32.py
movers/winterm.py
movers-1.2.dist-info/LICENSE.txt
movers-1.2.dist-info/METADATA
movers-1.2.dist-info/WHEEL
movers-1.2.dist-info/top_level.txt
movers-1.2.dist-info/RECORD
