Metadata-Version: 2.1
Name: movers
Version: 1.2
Summary: A great package for sound effects treatment.
Author: Lauren Jackson
Author-email: laurendevyork@gmail.com
Classifier: Programming Language :: Python :: 3
Classifier: License :: OSI Approved :: MIT License
Classifier: Operating System :: OS Independent
License-File: LICENSE.txt
